{"current":{"body_bg_color":"#fff","enable_body_bg_img":false,"body_bg_img":"","enable_blur_lazy_load":false,"enable_loadlogo":true,"loader_img":"shopify:\/\/shop_images\/sa.gif","loader_color":"#555","favicon":"shopify:\/\/shop_images\/cart_f2cb491f-d07f-450a-87c4-cdb2a5fc52c0.png","filter_category_title":"Les collections","trans_filter_category_title":"","filter_by_category_enable":true,"collection_category_limit":9,"filter_color_title":"color","trans_filter_color_title":"","filter_by_color_enable":false,"color_category_limit":8,"filter_by_color_option":"black,gray,orange,red,white,yellow,green,blue","filter_price_title":"price","trans_filter_price_title":"","filter_by_price_enable":false,"collection_price_limit":7,"filter_by_price_option":"below-$50, $51-$100, $101-$200, $201-$350, above-$350,$30-50","filter_size_title":"size","trans_filter_size_title":"","filter_by_size_enable":false,"size_category_limit":8,"filter_by_size_option":"S,M,L,XL","filter_brand_title":"brand","trans_filter_brand_title":"","filter_by_brand_enable":false,"filter_brand_limit":5,"brand_options":"The Solas,Dave's Killer Bread,Sunbeam Bread,Kit Kat,Oreo,Aashirvaad","filter_new_pro_title":"Plus demandés","trans_filter_new_pro_title":"","show_new_pro":true,"select_new_pro_coll":"les-mieux-notes","show_sidebar_banner":false,"Sidebar_bnr_img":"shopify:\/\/shop_images\/banner-3000-_Twitch_Video_Player_Banner-Max-Quality.jpg","sidebar_banner_link":"","show_sale_tag":true,"show_new_tag":true,"show_quickview":true,"show_compare":true,"show_wishlist":true,"product_tab_layout":"tab_1","show_color_swatches":true,"show_size_swatches":false,"swatch_style":"round","color_swatch_style1":"color_image","show_review_rating":true,"product_lable_style":"Round","product_lable_size":"large","grid_sale_label_position":"right","sale_label_bg_color":"#7bc00c","sale_label_text_color":"#555555","grid_new_label_position":"right","new_label_bg_color":"#7bc00c","new_label_text_color":"#252525","enable_360_view":true,"eneble_login_price":false,"group_video_features":"video","show_catelogue":false,"show_catelogue_price":false,"add_cart_btn":"normal","payment_url_1":"","payment_url_2":"","payment_url_3":"","payment_url_4":"","payment_url_5":"","popup_enable":true,"popup_ago_custom_time":true,"popup_disable_mobile":false,"popup_randomly_collection":"spices","buttom_message":"some one recently purchase this product.","trans_buttom_message":"","body_color":"#000000","timer_color":"#555555","timer_bg_color":"rgba(0,0,0,0)","timer_border_color":"#f2f2f2","border_cart_color":"#f2f2f2","primary_color":"#ff6e0b","secondary_color":"#252525","third_color":"#333","fourth_color":"#ffd200","primary_button_bg_color":"#ff6e0b","primary_button_text_color":"#eef2f4","primary_button_bg_color_hover":"#333333","primary_button_text_color_hover":"#eef2f4","secondary_button_bg_color":"#2b2015","secondary_button_text_color":"#eef2f4","secondary_button_bg_color_hover":"#ff6e0b","secondary_button_text_color_hover":"#eef2f4","top_header_bg_color":"#eef2f4","top_header_text_color":"#000000","logo_img_text_color":"0deg","header_bg_color":"#fff","header_search_bg_color":"#2b2015","header_shopping_text_color":"#252525","header_img_text_color":"0deg","nav_bg_color":"#2b2015","nav_link_color":"#eef2f4","nav_link_color_hover":"#333333","nav_link_category":"#ffffff","nav_title_category":"#1e0505","nav_title_hover":"#ff6e0b","nav_title_background":"#ff6e0b","title_left_offer":"#444444","title_icon_offer":"#ffffff","title_background_offer":"#ff4c3b","megamenu_title_color":"#ff4c3b","megamenu_link_color":"#333333","megamenu_link_color_hover":"#ff4c3b","breadcrumb_text_color":"#555","breadcrumb_active_color":"#999999","breadcrumb_color_hover":"#ff4c3b","footer_title_color":"#000000","footer_link_color":"#567e05","footer_link_color_hover":"#000000","btm_footer_text_color":"#777777","newsletter_enable":true,"newsletter_bg_color":"rgba(0,0,0,0)","newsletter_img":"shopify:\/\/shop_images\/newsletter_new1-_Twitch_Video_Player_Banner-Max-Quality_11c4e1ec-4c99-406f-b402-673807f314a8.jpg","newsletter_heading":"EpiLetter","trans_newsletter_heading":"","newsletter_text":"Rejoignez notre communauté d’EpiLovers et bénéficiez d’une livraison gratuite sur votre première commande","trans_newsletter_text":"","newsletter_form_url":"","header_layout":"header_1","display_sticky_header":false,"megamenu_bg_color":"#ffffff","deafult_color":"#ff4c3b","hot_color":"#335fed","new_color":"#ff4c3b","sale_color":"#ff3e11","deal_color":"#252525","footer_layout":"footer_4","footer_overlay":"dark-layout","enable_footer_bg_img":false,"footer_bg_img":"shopify:\/\/shop_images\/New_Project_1.jpg","enable_cookie_bar":true,"cookie_bar_bg_color":"#111111","cookie_msg":"We use cookies to improve our site and your shopping experience. By continuing to browse our site you accept our cookie policy.","cookie_bar_text_color":"#fdfdfd","cookie_btn_text":"Accept","cookie_btn_padding":"10px 0","cookie_bar_position":"bottom","type_primary_family":"Google_Montserrat_400_sans","type_seconadry_family":"Google_Montserrat_400_sans","show_multiple_currencies":true,"auto_curr_swticher":true,"currency_format":"money_with_currency_format","supported_currencies":"XAF USD","default_currency":"XAF","share_facebook":true,"share_twitter":true,"share_pinterest":true,"share_linked":true,"share_google":true,"social_twitter_link":"https:\/\/twitter.com","social_facebook_link":"https:\/\/www.facebook.com\/","social_google_link":"https:\/\/plus.google.com","social_linkedin_link":"https:\/\/www.linkedin.com","social_pinterest_link":"https:\/\/in.pinterest.com\/","social_instagram_link":"https:\/\/www.instagram.com\/","social_rss_link":"","social_youtube_link":"","add_to_cart_style":"popup","show_payment_img":true,"upsell_payment_img":"shopify:\/\/shop_images\/upsell-payment_600x40_0f4dc0c1-2303-4aa2-abdb-d7a5301259ee_1.jpg","eneble_upsell_products":true,"related_pro_title":"Customers who bought this item also.","trans_related_pro_title":"","shipping_calculator":"Enabled","shipping_calculator_heading":"Get shipping estimates","shipping_calculator_default_country":"United States","shipping_calculator_submit_button_label":"Calculate shipping","shipping_calculator_submit_button_label_disabled":"Calculating...","age_popup_enable":false,"age_popup_bg_color":"#fff","age_popup_heading":"Age Verification","trans_age_popup_heading":"","age_popup_text":"By clicking enter, I certify that I am over the age of 21 and will comply with the above statement.","trans_age_popup_text":"","exit_enable":false,"exit_color":"#fff","exit_heading":"wait!","trans_exit_heading":"","exit_heading_sub":"We want to give you <b>10% discount<\/b> for your first order","trans_exit_heading_sub":"","exit_popup_text":"Use discount code at checkout","trans_exit_popup_text":"","exit_img":"","exit_bnr_img":"shopify:\/\/shop_images\/30553_2_1_1.png","enable_fb_chat":false,"fb_color":"#0084ff","fb_page_id":"2123438804574660","greeting_title":"Hi! Welcome to PixelStrap Themes :) How can we help you?","enable_lang_switcher":true,"languages_support":"fr=Français,en=Anglais","checkout_header_image":"","checkout_logo_image":"","checkout_logo_position":"left","checkout_logo_size":"medium","checkout_body_background_image":"","checkout_body_background_color":"#fff","checkout_input_background_color_mode":"white","checkout_sidebar_background_image":"","checkout_sidebar_background_color":"#fafafa","checkout_heading_font":"-apple-system, BlinkMacSystemFont, 'Segoe UI', Roboto, Helvetica, Arial, sans-serif, 'Apple Color Emoji', 'Segoe UI Emoji', 'Segoe UI Symbol'","checkout_body_font":"-apple-system, BlinkMacSystemFont, 'Segoe UI', Roboto, Helvetica, Arial, sans-serif, 'Apple Color Emoji', 'Segoe UI Emoji', 'Segoe UI Symbol'","checkout_accent_color":"#197bbd","checkout_button_color":"#197bbd","checkout_error_color":"#e32c2b","show_group_image":"true","grid_color_swatches_style":"round","newsletter_text_color":"#000000","sections":{"top-header":{"type":"top-header","settings":{"enabled":true,"announcement_text":"-10% à partir d'un achat de 50 000 fcfa","trans_announcement_text":"{\"en\":\"Announce something here\", \"fr\":\"Annoncer quelque chose ici\", \"ar\":\"أعلن شيئا هنا\", \"de\":\"Kündigen Sie hier etwas an\", \"it\":\"Annuncia qualcosa qui\"}","phone_number":"67 78 10 49","trans_phone_number":"{\"en\":\"CALL US: 123-456-7890\", \"fr\":\"APPELEZ-NOUS AU 123-456-7890\", \"ar\":\"اتصل بنا: 123-456-7890\", \"de\":\"RUFEN SIE UNS an: 123-456-7890\", \"it\":\"CHIAMACI: 123-456-7890\"}","show_currency_picker":true,"show_language_picker":true}},"header":{"type":"header","settings":{"search_enable":true,"logo":"shopify:\/\/shop_images\/Epirapid-01.png","logo_max_width":"95","cart_text":"Votre panier","trans_cart_text":"","cart_img":"shopify:\/\/shop_images\/sac.png","map_img":"shopify:\/\/shop_images\/map-_Twitch_Video_Player_Banner-Max-Quality.jpg","cart_redirect":"ajax_cart"}},"megamenu":{"type":"megamenu","blocks":{"1537771062046":{"type":"parent-item-megamenu1","settings":{"menu_name":"PRODUITS","trans_menu_name":"{\"en\":\"mega menu \", \"fr\":\"méga menu\", \"ar\":\"القائمة ميجا\", \"de\":\"Mega-Menü\", \"it\":\"mega menu\"}","menu_link":"shopify:\/\/collections\/all","show_label":false,"label_text":"","trans_label_text":"","linklist_1":"menu-laterale","linklist_title_1":"Fruits","trans_custom_linklist_title_1":"","linklist_2":"animaux","linklist_title_2":"Animaux","trans_custom_linklist_title_2":"","linklist_3":"legumes","linklist_title_3":"Légumes","trans_custom_linklist_title_3":"","linklist_4":"feculents","linklist_title_4":"Féculents","trans_custom_linklist_title_4":"","linklist_5":"boissons","linklist_title_5":"Boissons","trans_custom_linklist_title_5":"","linklist_6":"matieres-grasses","linklist_title_6":"Matières grasses","trans_custom_linklist_title_6":"","show_custom_image":false}},"5cd38903-1019-400b-9bd4-35b0ebfd9011":{"type":"parent-item","settings":{"menu_name":"RECETTES","trans_menu_name":"","menu_link_1":"shopify:\/\/pages\/tous-les-produits","show_label":false,"label_text":"new","trans_label_text":""}},"8ebc73e7-c17a-42d2-9d1f-eb47ac3612fd":{"type":"parent-item","settings":{"menu_name":"TRAITEURS","trans_menu_name":"","show_label":false,"label_text":"new","trans_label_text":""}},"1538467515526":{"type":"parent-item","settings":{"menu_name":"RESTOS","trans_menu_name":"{\"en\":\"shop \", \"fr\":\"boutique\", \"ar\":\"متجر\", de\":\"Geschäft\", \"it\":\"negozio\"}","menu_link":"shopify:\/\/collections","show_label":false,"label_text":"new","trans_label_text":""}},"1537772196276":{"type":"parent-item-megamenu2","settings":{"menu_name":"PROMOS","trans_menu_name":"{\"en\":\"Trending \", \"fr\":\"Tendances\", \"ar\":\"الشائع\", \"de\":\"Trending\", \"it\":\"Trending\"}","menu_link":"#","show_label":true,"label_text":"En cours","trans_label_text":"{\"en\":\"new\", \"fr\":\"nouvelle\", \"ar\":\"الجديد\", de\":\"nouvelle\", \"it\":\"nuova\"}","linklist_1":"legumes","linklist_title_1":"En cours","linklist_title_12":"Bientôt finir","linklist_title_13":"Expire bientôt","linklist_title_14":"A venir","trans_linklist_title_1":"{\"en\":\"category\", \"fr\":\"Catégorie\", \"ar\":\"الفئة\", \"de\":\"Kategorie\", \"it\":\"categoria\"}","product_grid_title":"Légumes","product_grid_title_trans":"{\"en\": Fruits\", \"fr\":\" Fruits\", \"ar\":\"أزياء المرأة\", de\":\"Damenmode\", \"it\":\"La moda femminile\"}","megamenu_product_1":"betterave","megamenu_product_2":"courgettes","show_custom_image":true,"custom_image":"shopify:\/\/shop_images\/promoschoco_Twitch_Video_Player_Banner-Max-Quality_89e3b01a-2a5f-47b2-ab3a-b9b6952208f7.jpg","custom_image_url":"shopify:\/\/collections\/chocolat-promo","show_custom_image_1":true,"custom_image_1":"shopify:\/\/shop_images\/promosvins_Twitch_Video_Player_Banner-Max-Quality_166bd8f2-c2bf-4f26-9580-34612c0833e3.jpg","custom_image_url_1":"shopify:\/\/collections\/promotion-vins","show_custom_image_2":true,"custom_image_2":"shopify:\/\/shop_images\/promosjus_Twitch_Video_Player_Banner-Max-Quality_37f04492-ca9b-4c67-b954-202ff7616992.jpg","custom_image_url_2":"shopify:\/\/collections\/jus-de-fruits","show_custom_image_3":true,"custom_image_3":"shopify:\/\/shop_images\/promoslegumineuse_Twitch_Video_Player_Banner-Max-Quality_fbe95a43-ed01-4a50-9dce-b20a2282029f.jpg","custom_image_url_3":"shopify:\/\/collections\/legumuneuses-promos"}},"1536744284080":{"type":"verticle-menu","settings":{"v_menu_name":"Vegetables","trans_v_menu_name":"{\"en\":\"Vegetables \", \"fr\":\"Des légumes\", \"ar\":\"خضروات\", de\":\"Gemüse\", \"it\":\"Verdure\"}"}},"1536744436201":{"type":"verticle-menu","settings":{"v_menu_name":"fresh Fruits","trans_v_menu_name":"{\"en\":\"fresh fruits\", \"fr\":\"Fruits frais\", \"ar\":\"الفواكه الطازجة\", \"de\":\"Mega-Verkauf\", \"it\":\"frutta fresca\"}"}},"1536744498675":{"type":"verticle-menu","settings":{"v_menu_name":"Mango","trans_v_menu_name":"{\"en\":\"Mango\", \"fr\":\"Mangue\", \"ar\":\"مانجو\", \"de\":\"Mango\", \"it\":\"Mango\"}"}},"1536744529530":{"type":"verticle-menu","settings":{"v_menu_name":"Fresh Fruits","trans_v_menu_name":"{\"en\":\"fresh fruits\", \"fr\":\"Fruits frais\", \"ar\":\"الفواكه الطازجة\", \"de\":\"Mega-Verkauf\", \"it\":\"frutta fresca\"}"}},"1538546208273":{"type":"verticle-menu","settings":{"v_menu_name":"Mobile & tablet","trans_v_menu_name":"{\"en\":\"Mobile & tablet \", \"fr\":\"Mobile et tablette\", \"ar\":\"الجوال والكمبيوتر اللوحي\", de\":\"Handy & Tablet\", \"it\":\"Mobile e Tablet\"}"}}},"block_order":["1537771062046","5cd38903-1019-400b-9bd4-35b0ebfd9011","8ebc73e7-c17a-42d2-9d1f-eb47ac3612fd","1538467515526","1537772196276","1536744284080","1536744436201","1536744498675","1536744529530","1538546208273"],"settings":{"v_menu_enable":false,"v_view_more":"View More category","trans_more_cat":"{\"en\":\"view more category\", \"fr\":\"voir plus de catégorie\", \"ar\":\"عرض المزيد من الفئة\", de\":\"weitere Kategorie anzeigen\", \"it\":\"visualizza più categoria\"}","v_view_more_link":"shopify:\/\/collections","v_menu_text":"Prestation","trans_v_menu_text":"{\"en\":\" ALL DEPARTMENTS\", \"fr\":\"TOUS LES DÉPARTEMENTS\", \"ar\":\"جميع الإدارات\", \"de\":\"ALLE ABTEILUNGEN\", \"it\":\"TUTTI I DIPARTIMENTI\"}","h_menu_enable":true,"suumer_offer_enable":true,"summer_offer_title":"Guide","guide_img":"shopify:\/\/shop_images\/Epirapid-01_cfccfad5-43d2-42b5-a1fe-02e2f82826dc.png","summer_offer_title_12":"PériRapid'","guide_img_12":"shopify:\/\/shop_images\/Epirapid-01_cfccfad5-43d2-42b5-a1fe-02e2f82826dc.png","trans_summer_offer_title":"{\"en\":\"best offers\", \"fr\":\"meilleures offres\", \"ar\":\"أفضل العروض\", \"de\":\"beste Angebote\", \"it\":\"migliori offerte\"}","trans_summer_offer_title_11":"Title","offer_bnr_1":"shopify:\/\/shop_images\/ezgif-2-dce0885765f3_300x_73abf161-c318-4393-abd4-af412b29daa9.jpg","offer_bnr_11":"shopify:\/\/shop_images\/Epirapid-01_cfccfad5-43d2-42b5-a1fe-02e2f82826dc.png","offer_bnr_2":"shopify:\/\/shop_images\/ezgif-2-6946b296d807_300x_988a617d-1407-4754-889c-64c33ab93ec5.png","offer_bnr_21":"shopify:\/\/shop_images\/Epirapid-01_cfccfad5-43d2-42b5-a1fe-02e2f82826dc.png","offer_bnr_3":"shopify:\/\/shop_images\/ezgif-2-59e0781f5d3c_300x_e2ca6ef4-a806-4b8f-960b-2335b00dce0f.png","offer_bnr_31":"shopify:\/\/shop_images\/Epirapid-01_cfccfad5-43d2-42b5-a1fe-02e2f82826dc.png"}},"footer_bottom":{"type":"footer_bottom","blocks":{"1535619748100":{"type":"Custom-html","settings":{"footer_logo":"shopify:\/\/shop_images\/epinoi.png","footer_logo_max_width":"280","text":"EpiRapid' un clique et vous êtes livré."}},"1535619754531":{"type":"Menu","settings":{"title":"Navigations","footer_linklist":"liste-menu"}},"1535619761354":{"type":"Menu","settings":{"title":"Quick links","footer_linklist":""}},"1535619757850":{"type":"Info","settings":{"title":"Nos infos","address":"Cotonou immeuble de la direction générale de MTN Bénin","contact_info":"Contact : 67 78 10 49","email":"Email Us: contact@epirapid.com","fax":"Fax: 123456"}}},"block_order":["1535619748100","1535619754531","1535619761354","1535619757850"],"settings":{"show_social":true}},"list-collection-template":{"type":"list-collection-template","blocks":{"ad716d94-a90e-4468-b94b-5c044b4b304c":{"type":"collection","settings":{"collection":"tous-les-produits"}}},"block_order":["ad716d94-a90e-4468-b94b-5c044b4b304c"],"settings":{"collection_title":"COLLECTIONS","trans_collection_title":"","collection_img_height":"","display_type":"all","sort":"alphabetical","grid":"4","use_equal_height":false,"image_ratio":"ratio_landscape","image_size":"cover","image_position":"8"}},"collection-template":{"type":"collection-template","settings":{"pagination_option":"auto_loadmore","collection_sidebar":"left","sort_enable":true,"img_width":"full","use_equal_height":false,"image_ratio":"ratio_square","image_size":"cover","image_position":"2"}},"top-footer":{"type":"top-footer","blocks":{"1535713160126":{"type":"Contact","settings":{"title":"Contactez-nous","phone_number":"023-456-7950"}},"1535713163355":{"type":"Newsletter","settings":{"title":"Newsletter","form_url":""}}},"block_order":["1535713160126","1535713163355"],"settings":{"enabled":true}},"product-template":{"type":"product-template","settings":{"layout":"thumbnails-right","image_position":"pull-left","show_zoom_button":true,"show_wishlist_button":true,"show_qty_selector":true,"show_buy_now_btn":true,"show_share_buttons":true,"show_sku":false,"show_vendor":false,"show_type":false,"show_avalibity_option":false,"show_product_inventory":true,"inquery_title":"Avez-vous une question?","trans_inquery_title":"","show_countdown_timer":true,"countdown_timer_title":"","trans_countdown_title":"","product_opt_type":"color-swatches","swatches_option":"square","color_swatch_style":"color","size_guide_page":"","enable_tab_1":true,"tab_title_1":"Description","trans_tab_title_1":"","enable_tab_2":true,"tab_title_2":"Guide des tailles","trans_tab_title_2":"","enable_tab_3":true,"tab_title_3":"Vidéo","trans_tab_title_3":"","enable_tab_4":true,"tab_title_4":"Avis","trans_tab_title_4":"","show_resent_products":true,"resent_product_title":"Derniers produits consultés","trans_resent_pro_title":"","resent_product_product_length":"6","related_product_title":"Produits connexes","trans_related_product_title":"","related_product_product_length":"6"}},"about-us":{"type":"about-us","settings":{"about_enable":true,"about_description":"<h4>Sed ut perspiciatis unde omnis iste natus error sit voluptatem accusantium doloremque laudantium<\/h4>\n                <p>Sed ut perspiciatis unde omnis iste natus error sit voluptatem accusantium doloremque laudantium,<\/p>\n                <p>On the other hand, we denounce with righteous indignation and dislike men who are so beguiled and demoralized by the charms of pleasure of the moment, so blinded by desire, that they cannot foresee the pain and trouble that are bound to ensue; and equal blame belongs to those who fail in their duty through weakness of will, which is the same as saying through shrinking from toil and pain. These cases are perfectly simple and easy to distinguish. In a free hour, when our power of choice is untrammelled and when nothing prevents our being able to do what we like best, every pleasure is to be welcomed and every pain avoided. But in certain circumstances and owing to the claims of duty or the obligations of business it will frequently occur that pleasures have to be repudiated and annoyances accepted. The wise man therefore always holds in these matters to this principle of selection: he rejects pleasures to secure other greater pleasures, or else he endures pains to avoid worse pains.<\/p>","img_one":"shopify:\/\/shop_images\/3_66f05c94-7f23-43d5-a024-5ab43fb3e781.jpg","trans_about_description":"","img_two":"shopify:\/\/shop_images\/4.jpg","img_three":"","img_width":"full","use_equal_height":false,"image_ratio":"ratio2_1","image_size":"cover","image_position":"8"}},"testimonial":{"type":"testimonial","blocks":{"1535957157922":{"type":"testimonial","settings":{"testi_image":"shopify:\/\/shop_images\/2_d58bfb4f-e8a9-420d-afea-bf292a1f4840.jpg","testi_title":"Mark Jecno","trans_testi_title":"","testi_position":"Designer","trans_testi_position":"","testi_desc":"you how all this mistaken idea of denouncing pleasure and praising pain was born and I will give you a complete account of the system, and expound the actual teachings.","trans_testi_desc":""}},"1535957202572":{"type":"testimonial","settings":{"testi_image":"shopify:\/\/shop_images\/16.jpg","testi_title":"Mark Jecno","trans_testi_title":"","testi_position":"Designer","trans_testi_position":"","testi_desc":"you how all this mistaken idea of denouncing pleasure and praising pain was born and I will give you a complete account of the system, and expound the actual teachings.","trans_testi_desc":""}},"1535957503001":{"type":"testimonial","settings":{"testi_image":"shopify:\/\/shop_images\/17.jpg","testi_title":"Mark Jecno","trans_testi_title":"","testi_position":"Designer","trans_testi_position":"","testi_desc":"you how all this mistaken idea of denouncing pleasure and praising pain was born and I will give you a complete account of the system, and expound the actual teachings.","trans_testi_desc":""}}},"block_order":["1535957157922","1535957202572","1535957503001"],"settings":{"testimonial_enable":true,"slider_speed":3,"use_autoplay":true,"use_arrows":true,"use_dots":false,"use_loop":false,"use_equal_height":false,"image_ratio":"ratio_portrait","image_size":"cover","image_position":"8"}},"our-team":{"type":"our-team","blocks":{"1535957222976":{"type":"Team","settings":{"team_image":"shopify:\/\/shop_images\/1_35ed44a7-594b-450e-9ed4-a3b6e7ddc6b9.jpg","team_name":"Hilleri koel","trans_team_name":"","team_position":"hjgbjhbgnmnm","trans_team_position":""}},"1535957253878":{"type":"Team","settings":{"team_image":"shopify:\/\/shop_images\/2_5402e068-a062-4c5e-accf-b5572218ac83.jpg","team_name":"Hilleri koel","trans_team_name":"","team_position":"Ceo & Founder at company","trans_team_position":""}},"1535957264944":{"type":"Team","settings":{"team_image":"shopify:\/\/shop_images\/3_96ea3f3a-f6ac-4474-9f53-8810087ccac5.jpg","team_name":"Hilleri koel","trans_team_name":"","team_position":"Ceo & Founder at company","trans_team_position":""}},"1535957486321":{"type":"Team","settings":{"team_image":"shopify:\/\/shop_images\/4_cdbba0be-5e21-4ebf-a9d6-c7de7b5039fa.jpg","team_name":"Hilleri koel","trans_team_name":"","team_position":"Ceo & Founder at company","trans_team_position":""}}},"block_order":["1535957222976","1535957253878","1535957264944","1535957486321"],"settings":{"our_team_enable":true,"our_team_heading":"Our Team","trans_team_heading":"","use_equal_height":false,"image_ratio":"ratio_portrait","image_size":"cover","image_position":"8"}},"services":{"type":"services","blocks":{"1537269843341":{"type":"Service","settings":{"services_image":"shopify:\/\/shop_images\/service1_43f92e34-85b3-40d8-bd78-7c41413d048b.png","services_title":"free shipping","trans_services_title":"","services_desc":"World Wide Shipping","trans_services_desc":""}},"1537269845076":{"type":"Service","settings":{"services_image":"shopify:\/\/shop_images\/service2_26829e44-bfbf-4702-a2a8-ba928a9051c3.png","services_title":"free shipping","trans_services_title":"","services_desc":"World Wide Shipping","trans_services_desc":""}},"1537269846515":{"type":"Service","settings":{"services_image":"shopify:\/\/shop_images\/service3_1dc0ca12-043f-4b0f-b2b0-afaf0d69b8d0.png","services_title":"free shipping","trans_services_title":"","services_desc":"World Wide Shipping","trans_services_desc":""}},"1537269848076":{"type":"Service","settings":{"services_image":"shopify:\/\/shop_images\/service4_9fdf7760-fdee-449c-8df7-ad46f13927fc.png","services_title":"free shipping","trans_services_title":"","services_desc":"World Wide Shipping","trans_services_desc":""}},"1537269849452":{"type":"Service","settings":{"services_image":"shopify:\/\/shop_images\/service5_3e37ea12-a80a-47a5-8806-8095c2dfec57.png","services_title":"free shipping","trans_services_title":"","services_desc":"World Wide Shipping","trans_services_desc":""}}},"block_order":["1537269843341","1537269845076","1537269846515","1537269848076","1537269849452"],"settings":{"enabled":true}},"blog-template":{"type":"blog-template","settings":{"blog_limit":"4","blog_sidebar_position":"left","blog_date":true,"blog_auther":true,"blog_comment":true,"blog_sidebar_tags":true,"blog_sidebar_tags_title":"blog Tag","trans_blog_sidebar_tags_title":"","blog_sidebar_recent_post":true,"blog_sidebar_recentpost_title":"recent post","trans_blog_sidebar_abt_title":"","blog_sidebar_content":true,"blog_sidebar_abtt_title":"","trans_blog_sidebar_abtt_title":"","blog_sidebar_abtt_text":"","trans_blog_sidebar_abtt_text":"","img_width":"full","use_equal_height":false,"image_ratio":"ratio_landscape","image_size":"cover","image_position":"8"}},"copiright-footer":{"type":"copiright-footer","settings":{"show_payment_icons":true,"copyright_text":"<p>2018 - 19 Copy Right by Themeforest Powered by&nbsp;pixelstrep<\/p>"}},"contact-us":{"type":"contact-us","blocks":{"1536728280371":{"type":"Services","settings":{"service_title":"Nous contacter","service_desc":"<p>+229 67 78 10 49<\/p><p>+229 91 29 61 61<\/p>"}},"1536728282794":{"type":"Services","settings":{"service_title":"Adresse","service_desc":"<p>Cotonou, zone de l'aéroport, Immeuble direction générale MTN Bénin\n<br>\n<\/p>"}},"1536728285294":{"type":"Services","settings":{"service_title":"e-mail","service_desc":"<a href:=\"\">contact@epirapidgmail.com<\/a><br>\n<a href:=\"\">info@epirapid.com<\/a>"}},"1536728527589":{"type":"Services","settings":{"service_title":"fax","service_desc":"<a href:=\"\">support@epirapid.com<\/a><br>\n<a href:=\"\">info@epirapid.com<\/a>"}}},"block_order":["1536728280371","1536728282794","1536728285294","1536728527589"],"settings":{"contact_enable":true,"google_map_iframe":"<iframe src=\"https:\/\/www.google.com\/maps\/embed?pb=!1m18!1m12!1m3!1d3965.3441976040976!2d2.3966117143262995!3d6.349461426924705!2m3!1f0!2f0!3f0!3m2!1i1024!2i768!4f13.1!3m3!1m2!1s0x10235437787a2c53%3A0xba6334c98c1d9093!2sDirection%20G%C3%A9n%C3%A9rale%20de%20MTN%20Benin!5e0!3m2!1sfr!2sbj!4v1617647631132!5m2!1sfr!2sbj\" width=\"650\" height=\"450\" style=\"border:0;\" allowfullscreen=\"\" loading=\"lazy\"><\/iframe>"}},"faq-template":{"type":"faq-template","blocks":{"1537335728140":{"type":"general_question","settings":{"question_title":"How can I downgrade to an earlier version of Dummy Content?","trans_question_title":"","question_desc":"it look like readable English. Many desktop publishing packages and web page editors now use Lorem Ipsum as their default model text, and a search for 'lorem ipsum' will uncover many web sites still in their infancy. Various versions have evolved over the years,All the Lorem Ipsum generators on the Internet tend to repeat predefined chunks as necessary, making this the first true generator on the Internet. It uses a dictionary of over 200 Latin words, combined with a handful of model sentence structures","trans_question_desc":""}},"1540467121247":{"type":"general_question","settings":{"question_title":"Under what license are Regular Labs extensions released?","trans_question_title":"","question_desc":"it look like readable English. Many desktop publishing packages and web page editors now use Lorem Ipsum as their default model text, and a search for 'lorem ipsum' will uncover many web sites still in their infancy. Various versions have evolved over the years,All the Lorem Ipsum generators on the Internet tend to repeat predefined chunks as necessary, making this the first true generator on the Internet. It uses a dictionary of over 200 Latin words, combined with a handful of model sentence structures","trans_question_desc":""}},"1540467145351":{"type":"general_question","settings":{"question_title":"Under what license are Regular Labs extensions released?","trans_question_title":"","question_desc":"it look like readable English. Many desktop publishing packages and web page editors now use Lorem Ipsum as their default model text, and a search for 'lorem ipsum' will uncover many web sites still in their infancy. Various versions have evolved over the years,All the Lorem Ipsum generators on the Internet tend to repeat predefined chunks as necessary, making this the first true generator on the Internet. It uses a dictionary of over 200 Latin words, combined with a handful of model sentence structures","trans_question_desc":""}},"1537335731208":{"type":"seller_question","settings":{"question_title":"How can I upgrade from Shopify 2.5 to shopify 3?","trans_question_title":"","question_desc":"it look like readable English. Many desktop publishing packages and web page editors now use Lorem Ipsum as their default model text, and a search for 'lorem ipsum' will uncover many web sites still in their infancy. Various versions have evolved over the years,All the Lorem Ipsum generators on the Internet tend to repeat predefined chunks as necessary, making this the first true generator on the Internet. It uses a dictionary of over 200 Latin words, combined with a handful of model sentence structures it look like readable English. Many desktop publishing packages and web page editors now use Lorem Ipsum as their default model text, and a search for 'lorem ipsum' will uncover many web sites still in their infancy. Various versions have evolved over the years,All the Lorem Ipsum generators on the Internet tend to repeat predefined chunks as necessary, making this the first true generator on the Internet. It uses a dictionary of over 200 Latin words, combined with a handful of model sentence structures","trans_question_desc":""}},"1540467167730":{"type":"seller_question","settings":{"question_title":"What is shopify gold?","trans_question_title":"","question_desc":"it look like readable English. Many desktop publishing packages and web page editors now use Lorem Ipsum as their default model text, and a search for 'lorem ipsum' will uncover many web sites still in their infancy. Various versions have evolved over the years,All the Lorem Ipsum generators on the Internet tend to repeat predefined chunks as necessary, making this the first true generator on the Internet. It uses a dictionary of over 200 Latin words, combined with a handful of model sentence structures","trans_question_desc":""}},"1537336909095":{"type":"customer_question","settings":{"question_title":"Under what license are Regular Labs extensions released?","trans_question_title":"","question_desc":"it look like readable English. Many desktop publishing packages and web page editors now use Lorem Ipsum as their default model text, and a search for 'lorem ipsum' will uncover many web sites still in their infancy. Various versions have evolved over the years,All the Lorem Ipsum generators on the Internet tend to repeat predefined chunks as necessary, making this the first true generator on the Internet. It uses a dictionary of over 200 Latin words, combined with a handful of model sentence structures. it look like readable English. Many desktop publishing packages and web page editors now use Lorem Ipsum as their default model text, and a search for 'lorem ipsum' will uncover many web sites still in their infancy. Various versions have evolved over the years,All the Lorem Ipsum generators on the Internet tend to repeat predefined chunks as necessary, making this the first true generator on the Internet. It uses a dictionary of over 200 Latin words, combined with a handful of model sentence structures. it look like readable English. Many desktop publishing packages and web page editors now use Lorem Ipsum as their default model text, and a search for 'lorem ipsum' will uncover many web sites still in their infancy. Various versions have evolved over the years,All the Lorem Ipsum generators on the Internet tend to repeat predefined chunks as necessary, making this the first true generator on the Internet. It uses a dictionary of over 200 Latin words.","trans_question_desc":""}},"1540467193965":{"type":"customer_question","settings":{"question_title":"How can I downgrade to an earlier version of Dummy Content?","trans_question_title":"","question_desc":"it look like readable English. Many desktop publishing packages and web page editors now use Lorem Ipsum as their default model text, and a search for 'lorem ipsum' will uncover many web sites still in their infancy. Various versions have evolved over the years,All the Lorem Ipsum generators on the Internet tend to repeat predefined chunks as necessary, making this the first true generator on the Internet. It uses a dictionary of over 200 Latin words, combined with a handful of model sentence structures","trans_question_desc":""}}},"block_order":["1537335728140","1540467121247","1540467145351","1537335731208","1540467167730","1537336909095","1540467193965"],"settings":{"faq_enabled":true,"general_question_title":"GENERAL QUESTIONS","trans_question_title":"","seller_question_title":"QUESTIONS FOR SELLERS","trans_seller_question_title":"","customer_question_title":"QUESTIONS FOR CUSTOMER","trans_customer_question_title":""}},"article-template":{"type":"article-template","settings":{"blog_show_author":true,"blog_show_date":true,"blog_show_comment":true,"img_width":"auto","use_equal_height":false,"image_ratio":"ratio_landscape","image_size":"cover","image_position":"8"}},"cart-template":{"type":"cart-template","settings":{"page_title":"SHOPPING CART","trans_page_title":"","enable_cart_timer":true,"cart_timer_text":"Your cart will be expired in","cart_expiry_text":"Your cart is expired.","cart_timer_in_seconds":"1200"}},"header_3":{"type":"header_3","blocks":{"1537940526702":{"type":"verticle-menu","settings":{"v_menu_name":"vegitables","trans_v_menu_name":"","v_menu_url":"shopify:\/\/collections\/frontpage"}},"1537940529735":{"type":"verticle-menu","settings":{"v_menu_name":"fresh fruit","trans_v_menu_name":"","v_menu_url":"shopify:\/\/collections\/frontpage"}},"1538472321854":{"type":"verticle-menu","settings":{"v_menu_name":"new organics","trans_v_menu_name":"","v_menu_url":"shopify:\/\/collections\/best-collections"}},"1569407213692":{"type":"verticle-menu","settings":{"v_menu_name":"fresh grocery","trans_v_menu_name":"","v_menu_url":"shopify:\/\/collections\/featured-collection"}},"1569407238352":{"type":"verticle-menu","settings":{"v_menu_name":"Best Sale fruits","trans_v_menu_name":"","v_menu_url":"shopify:\/\/collections\/best-sale"}},"1569407267636":{"type":"verticle-menu","settings":{"v_menu_name":"Fresh Vegetables","trans_v_menu_name":"","v_menu_url":"shopify:\/\/collections\/best-collections"}},"1569407296279":{"type":"verticle-menu","settings":{"v_menu_name":"fresh organics","trans_v_menu_name":"","v_menu_url":"shopify:\/\/collections\/frontpage"}},"1537940538176":{"type":"parent-item","settings":{"menu_name":"Home","trans_menu_name":"","show_label":false,"label_text":"new","trans_label_text":""}},"1538472286288":{"type":"parent-item","settings":{"menu_name":"shop","trans_menu_name":"","menu_link":"shopify:\/\/collections\/frontpage","show_label":false,"label_text":"new","trans_label_text":""}},"1537940544561":{"type":"parent-item-megamenu1","settings":{"menu_name":"mega menu","trans_menu_name":"","show_label":true,"label_text":"new","trans_label_text":"","linklist_1":"","linklist_title_1":"FRUITS","trans_custom_linklist_title_1":"","linklist_2":"","linklist_title_2":"vegetables","trans_custom_linklist_title_2":"","linklist_3":"","linklist_title_3":"Quick links","trans_custom_linklist_title_3":"","linklist_4":"main-menu","linklist_title_4":"Main menu","trans_custom_linklist_title_4":"","linklist_5":"","linklist_title_5":"","trans_custom_linklist_title_5":"","linklist_6":"","linklist_title_6":"","trans_custom_linklist_title_6":"","show_custom_image":true}},"1569407748105":{"type":"parent-item-megamenu2","settings":{"menu_name":"features","trans_menu_name":"","show_label":false,"label_text":"deal","trans_label_text":"","linklist_1":"","linklist_title_1":"category","trans_linklist_title_1":"","product_grid_title":"","product_grid_title_trans":"","megamenu_product_1":"apricote","megamenu_product_2":"blackberry","show_custom_image":true,"custom_image_url":"shopify:\/\/collections"}},"1569407825504":{"type":"parent-child-item","settings":{"menu_name":"pages","trans_menu_name":"","submenu_linklist":"","show_label":false,"label_text":"hot","trans_label_text":""}},"1569407858818":{"type":"parent-item","settings":{"menu_name":"contact us","trans_menu_name":"","menu_link":"shopify:\/\/pages\/contact-us","show_label":true,"label_text":"new","trans_label_text":""}},"1569407877605":{"type":"parent-item","settings":{"menu_name":"blog","trans_menu_name":"","menu_link":"shopify:\/\/blogs\/news","show_label":false,"label_text":"new","trans_label_text":""}}},"block_order":["1537940526702","1537940529735","1538472321854","1569407213692","1569407238352","1569407267636","1569407296279","1537940538176","1538472286288","1537940544561","1569407748105","1569407825504","1569407858818","1569407877605"],"settings":{"eneble_serach":true,"logo_max_width":"170","cart_text":"Shopping Cart","trans_cart_text":"","cart_redirect":"ajax_cart","v_view_more":"view more","trans_more_cat":"","v_view_more_link":"shopify:\/\/collections\/best-sale","v_menu_text":"ALL DEPARTMENTS","trans_v_menu_text":"ALL DEPARTMENTS","suumer_offer_enable":true,"summer_offer_title":"summer offer","trans_summer_offer_title":"Title"}},"product-sticky-template":{"type":"product-sticky-template","settings":{"image_position":"pull-left","use_equal_height":false,"image_ratio":"ratio_landscape","image_size":"cover","image_position2":"8","show_wishlist_button":true,"show_avalibity_option":true,"show_sku":true,"show_brand":true,"show_qty_selector":true,"show_share_buttons":true,"show_product_inventory":true,"show_countdown_timer":true,"countdown_timer_title":"","enable_random_sale":false,"random_product_text":"","enable_product_active_view":false,"active_product_text":"","product_opt_type":"color-swatches","swatches_option":"square","color_swatch_style":"image_variant","size_guide_page":"size-guide","enable_tab_1":true,"tab_title_1":"Description","enable_tab_2":true,"tab_title_2":"Size Guide","enable_tab_3":true,"tab_title_3":"Video","enable_tab_4":true,"tab_title_4":"Review","related_product_title":"Related Products","related_product_product_length":"7"}},"footer-1":{"type":"footer-1","blocks":{"1537951469571":{"type":"Custom-html","settings":{"footer_logo":"shopify:\/\/shop_images\/Epirapid-01_cfccfad5-43d2-42b5-a1fe-02e2f82826dc.png","footer_logo_max_width":"180","text":"EpiRapid' un clique et vous êtes livré","show_downloads":true}},"1537951472082":{"type":"Menu","settings":{"title":"Links","trans_title":"","footer_linklist":""}},"1537951478482":{"type":"Menu","settings":{"title":"Links","trans_title":"","footer_linklist":""}},"1537951481431":{"type":"Menu","settings":{"title":"Links","trans_title":"","footer_linklist":"main-menu"}},"1569502818272":{"type":"Menu","settings":{"title":"Links","trans_title":"","footer_linklist":"footer"}}},"block_order":["1537951469571","1537951472082","1537951478482","1537951481431","1569502818272"],"settings":{"show_social":true,"footer_btm_linklist":"footer"}},"footer-2":{"type":"footer-2","blocks":{"1537951550768":{"type":"logo-newsletter","settings":{"footer_logo":"shopify:\/\/shop_images\/Epirapid-01_cfccfad5-43d2-42b5-a1fe-02e2f82826dc.png","footer_logo_max_width":"280","show_newsletter":true,"title":"Epiletter","title_newsletter":"","form_url":""}},"1537951553884":{"type":"Custom-html","settings":{"title":"About us","trans_title":"","text":"It is a long established fact that a reader will be distracted by the readable content.","trans_text":"","show_downloads":true}},"1537951556845":{"type":"Menu","settings":{"title":"category","transalte_title":"","footer_linklist":""}},"1537951561210":{"type":"Menu","settings":{"title":"menu","transalte_title":"","footer_linklist":"main-menu"}},"1537951564467":{"type":"Menu","settings":{"title":"quick links","transalte_title":"","footer_linklist":""}},"1538461034209":{"type":"Info","settings":{"title":"Store Info","trans_title":"","address":"Fiot Fashion Demo Store Demo Store USA","trans_address":"","email":"Email Us: Support@Fiot.com","trans_email":"","fax":"Fax: 123456","trans_fax":"","animation_style":"slideInUp","animation_time":"0.5s"}}},"block_order":["1537951550768","1537951553884","1537951556845","1537951561210","1537951564467","1538461034209"],"settings":{"show_social":true,"footer_btm_linklist":""}},"1538114027245":{"type":"partner-logo","disabled":true,"blocks":{"1538114027245-1":{"type":"logo_image","settings":{"image":"shopify:\/\/shop_images\/bss-_Twitch_Video_Player_Banner-Max-Quality.jpg"}},"1538114027245-2":{"type":"logo_image","settings":{"image":"shopify:\/\/shop_images\/erevan-_Twitch_Video_Player_Banner-Max-Quality.jpg"}},"1538114027245-3":{"type":"logo_image","settings":{"image":"shopify:\/\/shop_images\/fsa-_Twitch_Video_Player_Banner-Max-Quality.jpg"}},"1538114027245-4":{"type":"logo_image","settings":{"image":"shopify:\/\/shop_images\/mont_sina-_Twitch_Video_Player_Banner-Max-Quality.jpg"}},"1538114027245-5":{"type":"logo_image","settings":{"image":"shopify:\/\/shop_images\/sobebra-_Twitch_Video_Player_Banner-Max-Quality.jpg"}},"1538115029376":{"type":"logo_image","settings":{"image":"shopify:\/\/shop_images\/songha-_Twitch_Video_Player_Banner-Max-Quality.jpg"}},"1538115031647":{"type":"logo_image","settings":{"image":"shopify:\/\/shop_images\/aqua-_Twitch_Video_Player_Banner-Max-Quality.jpg"}},"1538115055637":{"type":"logo_image","settings":{"image":"shopify:\/\/shop_images\/posso-_Twitch_Video_Player_Banner-Max-Quality.jpg"}},"1538115064505":{"type":"logo_image","settings":{"image":"shopify:\/\/shop_images\/u-_Twitch_Video_Player_Banner-Max-Quality.jpg"}}},"block_order":["1538114027245-1","1538114027245-2","1538114027245-3","1538114027245-4","1538114027245-5","1538115029376","1538115031647","1538115055637","1538115064505"],"settings":{"enabled":true,"enable_b_space":true,"enable_bg_color":false,"slider_speed":3,"use_autoplay":true,"use_arrows":true,"use_dots":false,"use_loop":false,"slidetoshow":6,"image_per_row":"8"}},"footer-4":{"type":"footer-4","blocks":{"1538460475321":{"type":"Custom-html","settings":{"footer_logo":"shopify:\/\/shop_images\/Epirapid-01_cfccfad5-43d2-42b5-a1fe-02e2f82826dc.png","footer_logo_max_width":"100","text":"Marché, resto ou traiteurs?\nDonnez vie à vos envies à temps!","trans_text":"","show_social":true}},"1538460478022":{"type":"newsletter","settings":{"title":"EpiLetter","trans_news_title":"","subscribe_text":"Rejoignez notre communauté d'EpiLovers","trans_subscribe_text":"","form_url":"","show_downloads":true}},"1538460480832":{"type":"Menu","settings":{"title":"navigation","trans_title":"","footer_linklist":""}},"1538460483967":{"type":"Menu","settings":{"title":"quick link","trans_title":"","footer_linklist":""}},"1538460489951":{"type":"Menu","settings":{"title":"category","trans_title":"","footer_linklist":""}},"1538460486596":{"type":"Info","settings":{"title":"EpiInfo","trans_title":"","address":"Cotonou aéroport, immeuble Direction générale MTN","trans_address":"","email":"Email : Support@EpiRapid.com","trans_email":"","fax":"Tel : 67 78 10 49","trans_fax":""}}},"block_order":["1538460475321","1538460478022","1538460480832","1538460483967","1538460489951","1538460486596"],"settings":{"footer_btm_linklist":"footer"}},"footer-5":{"type":"footer-5","blocks":{"1538461728898":{"type":"Custom-html","settings":{"footer_logo":"shopify:\/\/shop_images\/logo_86736358-3d91-42b4-86a7-003a2d2e6260.png","footer_logo_max_width":"280","text":"It is a long established fact that a reader will be distracted by the readable content.","trans_text":"It is a long established fact that a reader will be distracted by the readable content.","show_downloads":true,"payment_1":"shopify:\/\/shop_images\/Android_e1cdfb1c-71c1-42a3-9a31-c41f61cb2fd1.png","payment_1_link":"","payment_2":"shopify:\/\/shop_images\/Apple_5ed7d9f4-4b7d-4bbf-829e-775434cd7fa5.png","payment_2_link":""}},"1538461731636":{"type":"newsletter","settings":{"title":"Newsletter","trans_title":"Newsletter","form_url":"","subscribe_text":"Subscribe to our newsletter and Stay to update"}},"1538461737698":{"type":"Menu","settings":{"title":"Links","trans_title":"Links","footer_linklist":"footer"}},"1538461741701":{"type":"Menu","settings":{"title":"Links","trans_title":"Links","footer_linklist":"footer"}},"1538461744538":{"type":"Menu","settings":{"title":"Links","trans_title":"Links","footer_linklist":"footer"}},"1538461747258":{"type":"Info","settings":{"title":"Store Info","trans_title":"","address":"Fiot Fashion Demo Store Demo Store USA","trans_address":"","email":"Email Us: Support@Fiot.com","trans_email":"","fax":"Fax: 123456","trans_fax":"","animation_style":"slideInUp","animation_time":"0.5s"}}},"block_order":["1538461728898","1538461731636","1538461737698","1538461741701","1538461744538","1538461747258"],"settings":{"show_social":true,"enable_space":true,"show_payment_icons":true,"copyright_text":"<p>2018 - 19 Copy Right by Themeforest Powered by Webiots<\/p>"}},"header-4":{"type":"header-4","settings":{"eneble_black_bg":true,"announcement_text":"Announce something here","trans_announcement_text":"","phone_number":"CALL US: 123-456-7890","trans_phone_number":"","show_currency_picker":true,"show_language_picker":false,"eneble_serach":true,"logo_max_width":"250"}},"product-three-column":{"type":"product-three-column","settings":{"layout":"thumbnails-left","image_position":"pull-left","inquery_title":"Have a questions?","trans_inquery_title":"","show_wishlist_button":true,"show_avalibity_option":true,"show_sku":true,"show_brand":true,"show_qty_selector":true,"show_product_inventory":true,"show_share_buttons":true,"show_countdown_timer":true,"countdown_timer_title":"","trans_countdown_title":"","product_opt_type":"color-swatches","swatches_option":"square","color_swatch_style":"color_image","size_guide_page":"","show_payment_icon":true,"tab_title_1":"Description","trans_tab_title_1":"","enable_tab_2":true,"tab_title_2":"Size Guide","trans_tab_title_2":"","enable_tab_3":true,"tab_title_3":"Video","trans_tab_title_3":"","enable_tab_4":true,"tab_title_4":"Review","trans_tab_title_4":"","related_product_title":"Related Products","trans_related_product_title":"","related_product_product_length":"6"}},"1568787966576":{"type":"parallax-banner","disabled":true,"settings":{"enabled":true,"to_space":false,"section_padding":"150px 0px 150px 0px","enabled_torn_section":false,"enabled_overlay":true,"banner_img":"shopify:\/\/shop_images\/banniere2.jpg","alignment":"text-left","position":"p-left","title":"best deal","trans_title":"","title_color":"#ff4c3b","subtitle":"new designs","trans_subtitle":"","subtitle_color":"#ffffff","bottom_title":"Summer Sale","trans_bottom_title":"","bottom_title_color":"#ffffff","enabled_button":true,"text_layout":"style-1"}},"1568788951664":{"type":"hot_deal","disabled":true,"blocks":{"1568788951664-0":{"type":"Tab","settings":{"title":"best sale","trans_title":"","tab_collection":"chocolat","display_rating":true,"display_desc":true,"desc_words":"100","display_timer":true,"timer_title":"Timer Reminder","trans_timer_title":"","tab_title":"Today's Hot Deal","timer_date":"Sep 5, 2020"}},"1568788951664-1":{"type":"Tab","settings":{"title":"top collections","trans_title":"","tab_collection":"chocolat","display_rating":true,"display_desc":true,"desc_words":"100","display_timer":true,"timer_title":"Timer Reminder","trans_timer_title":"","tab_title":"Today's Hot Deal","timer_date":"Sep 5, 2020"}}},"block_order":["1568788951664-0","1568788951664-1"],"settings":{"enabled":true,"bottom_space":true,"media_space":true,"enabled_slidercolums":true,"title":"A vendre","trans_title":"","sale_collection":"chocolat","tab_title":"Today's Hot Deal","trans_tab_title":"","display_sale_slider":true}},"header-5":{"type":"header-5","blocks":{"1568797006072":{"type":"parent-item","settings":{"menu_name":"Home","trans_menu_name":"","show_label":true,"label_text":"new","trans_label_text":""}},"1568797013084":{"type":"parent-item-megamenu1","settings":{"menu_name":"megamenu","trans_menu_name":"","menu_link":"#","show_label":false,"label_text":"sale","trans_label_text":"","linklist_1":"","linklist_title_1":"category","trans_custom_linklist_title_1":"","linklist_2":"main-menu","linklist_title_2":"Main menu","trans_custom_linklist_title_2":"","linklist_3":"","linklist_title_3":"vegetables","trans_custom_linklist_title_3":"","linklist_4":"","linklist_title_4":"Quick links","trans_custom_linklist_title_4":"","linklist_5":"","linklist_title_5":"","trans_custom_linklist_title_5":"","linklist_6":"","linklist_title_6":"","trans_custom_linklist_title_6":"","show_custom_image":true}},"1568797028027":{"type":"parent-item","settings":{"menu_name":"shop","trans_menu_name":"","menu_link":"shopify:\/\/collections","show_label":false,"label_text":"new","trans_label_text":""}},"1568797017139":{"type":"parent-item-megamenu2","settings":{"menu_name":"Trending","trans_menu_name":"","show_label":false,"label_text":"deal","trans_label_text":"","linklist_1":"","linklist_title_1":"category","trans_linklist_title_1":"","product_grid_title":"","product_grid_title_trans":"","megamenu_product_1":"apricote","megamenu_product_2":"dragon-fruit","show_custom_image":true}},"1568797020886":{"type":"parent-child-item","settings":{"menu_name":"pages","trans_menu_name":"","submenu_linklist":"","show_label":true,"label_text":"hot","trans_label_text":""}},"1568798510123":{"type":"parent-item","settings":{"menu_name":"contact us","trans_menu_name":"","menu_link":"shopify:\/\/pages\/contact-us","show_label":false,"label_text":"new","trans_label_text":""}},"1569479632705":{"type":"parent-item","settings":{"menu_name":"collections","trans_menu_name":"","menu_link":"shopify:\/\/collections\/frontpage","show_label":false,"label_text":"new","trans_label_text":""}}},"block_order":["1568797006072","1568797013084","1568797028027","1568797017139","1568797020886","1568798510123","1569479632705"],"settings":{"eneble_serach":true,"logo_max_width":"170","cart_text":"Shopping Cart","trans_cart_text":"","cart_redirect":"ajax_cart","v_view_more":"","trans_more_cat":"","v_menu_text":"ALL DEPARTMENTS","trans_v_menu_text":"ALL DEPARTMENTS","suumer_offer_enable":true,"summer_offer_title":"BEST OFFERS","trans_summer_offer_title":"Title"}},"1569469321673":{"type":"instragram","disabled":true,"settings":{"enabled":true,"slideshow_width":"full-width","post_limit":"7","instagram_title":"","insta_user_id":"8295761913","insta_access_token":"8295761913.aa0cb6f.2914e9f04dd343b8a57d9dc9baca91cc"}},"1569491996226":{"type":"featured_collections","disabled":true,"blocks":{"1569491996226-0":{"type":"Collection","settings":{"banner_image":"shopify:\/\/shop_images\/photo_spice-High-Quality.jpg","collection":"meilleurs-ventes","enabled_info":true,"title_top":"Les catégories","trans_title_top":"","title":"Epices","trans_title":"","title_bottom":"-16%","trans_title_bottom":"","btn_txt":"Achetez Maintenant","trans_btn_txt":"","banner_color_style":"banner-green","enabled_dark_btn":true,"text_style":"light-theme"}},"1569491996226-1":{"type":"Collection","settings":{"banner_image":"shopify:\/\/shop_images\/photo_cereales-High-Quality.jpg","collection":"meilleurs-ventes","enabled_info":true,"title_top":"Soldes","trans_title_top":"","title":"Céréales","trans_title":"","title_bottom":"-50%","trans_title_bottom":"","btn_txt":"Acheter maintenant","trans_btn_txt":"","banner_color_style":"banner-green","enabled_dark_btn":true,"text_style":"dark_theme"}},"1569491996226-2":{"type":"Collection","settings":{"banner_image":"shopify:\/\/shop_images\/photo_vegetable-High-Quality.jpg","collection":"meilleurs-ventes","enabled_info":true,"title_top":"Soldes","trans_title_top":"","title":"Légumes","trans_title":"","title_bottom":"-25%","trans_title_bottom":"","btn_txt":"Acheter maintenant","trans_btn_txt":"","banner_color_style":"banner-green","enabled_dark_btn":false,"text_style":"dark_theme"}}},"block_order":["1569491996226-0","1569491996226-1","1569491996226-2"],"settings":{"enabled":true,"enabled_layout_2":true,"tab_title":"Today's Hot Deal","use_equal_height":false,"image_ratio":"ratio_landscape","image_size":"cover","image_position2":"8"}},"1569495574717":{"type":"special-tab","blocks":{"1569495574717-0":{"type":"Tab","settings":{"title":"Fruits","trans_title":"","tab_collection":"fruits","display_rating":true,"display_desc":true,"desc_words":"100","product_limit":"8","product_per_row":"6"}},"1569495574717-1":{"type":"Tab","settings":{"title":"Légumes","trans_title":"","tab_collection":"legume-meilleures-ventes","display_rating":true,"display_desc":true,"desc_words":"100","product_limit":"8","product_per_row":"6"}}},"block_order":["1569495574717-0","1569495574717-1"],"settings":{"enabled":true,"bottom_space":true,"media_space":true,"enabled_slidercolums":true,"tab_title":"Explorer nos meilleures ventes","trans_tab_title":"","display_sale_slider":false,"slider_speed":3,"use_autoplay":true,"use_arrows":true,"use_dots":false,"use_loop":true,"slidetoshow":5,"slidetoshow_1367":4,"slidetoshow_1024":2,"slidetoshow_767":2,"slidetoshow_420":2}},"1571476783856":{"type":"promotion-products","disabled":true,"blocks":{"1571476783856-0":{"type":"image","settings":{"banner_img":"shopify:\/\/shop_images\/promosjus_Twitch_Video_Player_Banner-Max-Quality.jpg"}},"24ddb6bd-2f27-4453-b57c-c852b5d604d9":{"type":"image","settings":{"banner_img":"shopify:\/\/shop_images\/recette1-_Twitch_Video_Player_Banner-Max-Quality.jpg"}}},"block_order":["1571476783856-0","24ddb6bd-2f27-4453-b57c-c852b5d604d9"],"settings":{"enabled":true,"enabled_top_space":true,"trending_pro_enabled":true,"title":"Les mieux notés","collection":"les-mieux-notes","product_limit":"18","product_per_row":"4","use_equal_height":false,"image_ratio":"ratio_landscape","image_size":"cover","image_position2":"8","slider_speed":3,"use_autoplay":true,"use_arrows":true,"use_dots":false,"use_loop":true,"slidetoshow":3,"slidetoshow_1367":3,"slidetoshow_1024":3,"slidetoshow_767":2,"slidetoshow_420":1}},"1569494046757":{"type":"services-2","disabled":true,"blocks":{"1569494046757-0":{"type":"Service","settings":{"services_image":"shopify:\/\/shop_images\/liste.png","services_title":"Entrez votre liste de course","trans_services_title":"","banner_link":"shopify:\/\/pages\/entrez-votre-liste-de-course","services_desc":"World Wide Shipping","trans_services_desc":""}},"1569494046757-1":{"type":"Service","settings":{"services_image":"shopify:\/\/shop_images\/microphone.png","services_title":"Dictez votre liste de course","trans_services_title":"","banner_link":"shopify:\/\/pages\/dictez-votre-liste-de-course","services_desc":"Online Service","trans_services_desc":""}},"1569494046757-2":{"type":"Service","settings":{"services_image":"shopify:\/\/shop_images\/camera.png","services_title":"Photographier votre liste de course","trans_services_title":"","banner_link":"shopify:\/\/pages\/photographiez-votre-liste-de-course","services_desc":"New Online offers","trans_services_desc":""}},"1569494046757-3":{"type":"Service","settings":{"services_image":"shopify:\/\/shop_images\/scan.png","services_title":"Scanner votre produit","trans_services_title":"","banner_link":"shopify:\/\/pages\/scannez-votre-liste-de-course","services_desc":"ONLY FOR NEW SELLERS","trans_services_desc":""}}},"block_order":["1569494046757-0","1569494046757-1","1569494046757-2","1569494046757-3"],"settings":{"enabled":true,"animation_style":"slideInUp","animation_time":"0.5s"}},"16172081738e1718fd":{"type":"hot_deal","disabled":true,"blocks":{"1617208173d011a0c6-0":{"type":"Tab","settings":{"title":"Product Tab","trans_title":"","tab_collection":"","display_rating":true,"display_desc":true,"desc_words":"100","display_timer":true,"timer_title":"Timer Reminder","trans_timer_title":"","tab_title":"Today's Hot Deal","timer_date":"Sep 5, 2018"}},"1617208173d011a0c6-1":{"type":"Tab","settings":{"title":"Product Tab","trans_title":"","tab_collection":"","display_rating":true,"display_desc":true,"desc_words":"100","display_timer":true,"timer_title":"Timer Reminder","trans_timer_title":"","tab_title":"Today's Hot Deal","timer_date":"Sep 5, 2018"}}},"block_order":["1617208173d011a0c6-0","1617208173d011a0c6-1"],"settings":{"enabled":true,"bottom_space":true,"media_space":true,"enabled_slidercolums":true,"title":"Sale","trans_title":"","sale_collection":"","tab_title":"Today's Hot Deal","trans_tab_title":"","display_sale_slider":true}},"16172743112c17da1b":{"type":"featured_category","disabled":true,"blocks":{"1617274311488e4fe0-0":{"type":"collection","settings":{"cot_image":"shopify:\/\/shop_images\/fraise.png","collection":"fruits","title":"fraise","trans_title":"","subheading":"-5%","trans_subheading":"","btn_txt":"Achetez maintenant","trans_btn_txt":""}},"1617274311488e4fe0-1":{"type":"collection","settings":{"cot_image":"shopify:\/\/shop_images\/pomme.png","collection":"meilleurs-ventes","title":"Pomme","trans_title":"","subheading":"-5%","trans_subheading":"","btn_txt":"Achetez maintenant","trans_btn_txt":""}},"1617274311488e4fe0-2":{"type":"collection","settings":{"cot_image":"shopify:\/\/shop_images\/orange.png","collection":"meilleurs-ventes","title":"Orange","trans_title":"","subheading":"-5%","trans_subheading":"","btn_txt":"Achetez maintenant","trans_btn_txt":""}},"1617274311488e4fe0-3":{"type":"collection","settings":{"cot_image":"shopify:\/\/shop_images\/tomate_3673324c-89ba-41af-8cdf-1144000757a4.png","collection":"","title":"Tomate","trans_title":"","subheading":"-5%","trans_subheading":"","btn_txt":"Achetez maintenant","trans_btn_txt":""}}},"block_order":["1617274311488e4fe0-0","1617274311488e4fe0-1","1617274311488e4fe0-2","1617274311488e4fe0-3"],"settings":{"enabled":true,"use_equal_height":false,"image_ratio":"ratio_landscape","image_size":"cover","image_position2":"8","title":"Promotions","trans_title":"","cat_per_row":"4"}},"16172760213470fe16":{"type":"colums-with-banner","blocks":{"161727602174760a7f-0":{"type":"banner","settings":{"image":"shopify:\/\/shop_images\/banniere770x990_Twitch_Video_Player_Banner-Max-Quality.jpg"}},"161727602174760a7f-1":{"type":"column","settings":{"title":"Fruits","trans_title":"","collection":"fruits"}},"161727602174760a7f-2":{"type":"column","settings":{"title":"Légumes","trans_title":"","collection":"legume-meilleures-ventes"}},"161727602174760a7f-3":{"type":"column","settings":{"title":"Animaux","trans_title":"","collection":"meilleures-vente-viande"}},"161727602174760a7f-4":{"type":"banner","settings":{"image":"shopify:\/\/shop_images\/banniere770x890_Twitch_Video_Player_Banner-Max-Quality.jpg"}}},"block_order":["161727602174760a7f-0","161727602174760a7f-1","161727602174760a7f-2","161727602174760a7f-3","161727602174760a7f-4"],"settings":{"enabled":true,"enable_bg_img":true,"tab_title":"Bondisser sur nos produits à moins de 3000 f","enabled_overlay":true,"image_bg_color":"#f2f2f2","slider":"shopify:\/\/shop_images\/planche_texture-Max-Quality.jpg","slider_height":75,"slider_speed":3,"use_autoplay":true,"use_arrows":true,"use_dots":false,"use_loop":false,"use_equal_height":false,"image_ratio":"ratio_landscape","image_size":"cover","image_position2":"7"}},"1617879703be2a5e7a":{"type":"trending_product_slider","disabled":true,"settings":{"enabled":true,"top_space":true,"bg_color_enable":false,"use_equal_height":false,"image_ratio":"ratio_landscape","image_size":"cover","image_position":"8","title":"Les nouveautés","trans_title_arrivals":"","collection":"les-nouveautes","slider_speed":3,"use_autoplay":true,"use_arrows":true,"use_dots":false,"use_loop":true,"slidetoshow":4,"slidetoshow_1367":4,"slidetoshow_1024":3,"slidetoshow_767":2,"slidetoshow_420":1}},"allproduct-template":{"type":"allproduct-template","settings":{"banner_img":"shopify:\/\/shop_images\/patate-_Twitch_Video_Player_Banner-Max-Quality.jpg","pagination_option":"default","collection_sidebar":"left","sort_enable":true,"img_width":"full","use_equal_height":false,"image_ratio":"ratio_landscape","image_size":"cover","image_position":"8"}},"1618919299d327db3e":{"type":"product_tab_with_banner","blocks":{"1618919299ddbd7f06-0":{"type":"Tab","settings":{"title":"Recettes Africaines","trans_title":"","tab_collection":"recettes-africaines"}},"1618919299ddbd7f06-1":{"type":"Tab","settings":{"title":"Recettes Américaines","trans_title":"","tab_collection":"recettes-americaines"}},"1618919299ddbd7f06-2":{"type":"Tab","settings":{"title":"Recettes Asiatiques","trans_title":"","tab_collection":"recettes-asiatiques"}},"1618919299ddbd7f06-3":{"type":"Tab","settings":{"title":"Recettes Européennes","trans_title":"","tab_collection":"recettes-europeennes"}},"1618919299ddbd7f06-4":{"type":"Banner","settings":{"banner_img":"shopify:\/\/shop_images\/banniere690x795_Twitch_Video_Player_Banner-Max-Quality.jpg","custom_html":"<!--h2> Vos recettes <\/h2><h1>EpiTraiteur<span>50%<\/span><span>off<\/span>\n<span>Des cuisiniers prêts à vous cuisiner les meilleurs plats des quatre coins du monde<\/span-->","title":"Commander","trans_button_title":""}}},"block_order":["1618919299ddbd7f06-0","1618919299ddbd7f06-1","1618919299ddbd7f06-2","1618919299ddbd7f06-3","1618919299ddbd7f06-4"],"settings":{"enabled":true,"tab_title":"Tester nos délicieuses recettes","trans_tab_title":"","use_equal_height":false,"image_ratio":"ratio_landscape","image_size":"cover","image_position":"8"}},"16189962437f7a452d":{"type":"top-footer","disabled":true,"blocks":{"161899624399e5d907-0":{"type":"Contact","settings":{"title":"Contact us","phone_number":"023-456-7950"}},"161899624399e5d907-1":{"type":"Newsletter","settings":{"title":"Newsletter","form_url":""}}},"block_order":["161899624399e5d907-0","161899624399e5d907-1"],"settings":{"enabled":true}},"16189964209f69adb2":{"type":"featured_product_slider","blocks":{"161899642003aca4a2-0":{"type":"column","settings":{"title":"FRUITS","trans_title":"","collection":"melange-fruits"}},"161899642003aca4a2-1":{"type":"column","settings":{"title":"Boissons","trans_title":"","collection":"melange-boisson"}},"161899642003aca4a2-2":{"type":"column","settings":{"title":"Animaux","trans_title":"","collection":"melange-animaux"}},"161899642003aca4a2-3":{"type":"column","settings":{"title":"Féculents","trans_title":"","collection":"melange-feculents-1"}},"58a4c1e8-bdfa-4bfd-beff-d486eed02f32":{"type":"column","settings":{"title":"légumes","trans_title":"","collection":"melange-legume"}}},"block_order":["161899642003aca4a2-0","161899642003aca4a2-1","161899642003aca4a2-2","161899642003aca4a2-3","58a4c1e8-bdfa-4bfd-beff-d486eed02f32"],"settings":{"enabled":true,"enable_bg_img":true,"tab_title":"flirter avec nos produits rares","enabled_overlay":true,"image_bg_color":"#f2f2f2","slider":"shopify:\/\/shop_images\/fond_smart_basket.jpg","slider_height":75,"slider_speed":3,"use_autoplay":true,"use_arrows":true,"use_dots":false,"use_loop":false,"use_equal_height":false,"image_ratio":"ratio_landscape","image_size":"cover","image_position2":"8"}},"1618996591630da601":{"type":"mixed_product_slider","blocks":{"161899659143f9a027-0":{"type":"Banner","settings":{"banner_img":"shopify:\/\/shop_images\/ananas_ba35820b-13e4-4a64-ba4f-b45004d6c3c4.jpg","custom_html":"<h2> 100% <span>Naturel<\/span>\n<\/h2>"}},"161899659143f9a027-1":{"type":"Slider","settings":{"slider_title":"Féculents","trans_slider_title":"","collection":"melange-feculents-1"}},"161899659143f9a027-2":{"type":"Product","settings":{"title":"Produit vedette","trans_title":"","special_product":"horgelus"}},"161899659143f9a027-3":{"type":"Slider","settings":{"slider_title":"Boissons","trans_slider_title":"","collection":"melange-boisson"}}},"block_order":["161899659143f9a027-0","161899659143f9a027-1","161899659143f9a027-2","161899659143f9a027-3"],"settings":{"enabled":true,"tab_title":"découvrer nos nouveautés","use_equal_height":false,"image_ratio":"ratio_landscape","image_size":"cover","image_position":"8"}},"1619099473c85bae64":{"type":"hot_deal","blocks":{"1619099473c85bae64-0":{"type":"Tab","settings":{"title":"Fruits","trans_title":"","tab_collection":"melange-fruits","display_rating":true,"display_desc":true,"desc_words":"100","display_timer":true,"timer_title":"Rappel de la minuterie","trans_timer_title":"","tab_title":"Today's Hot Deal","timer_date":"May 22, 2021"}}},"block_order":["1619099473c85bae64-0"],"settings":{"enabled":true,"bottom_space":true,"media_space":false,"enabled_slidercolums":true,"title":"Plus vendu","trans_title":"","sale_collection":"les-mieux-notes","tab_title":"fonder pour nos promos","trans_tab_title":"","display_sale_slider":true}},"16191035634f7425c1":{"type":"featured_collections","blocks":{"16191035634f7425c1-0":{"type":"Collection","settings":{"banner_image":"shopify:\/\/shop_images\/saisirlist.gif","collection":"","enabled_info":true,"title_top":"Rechercher votre produit par note vocale","trans_title_top":"","title":"","trans_title":"","title_bottom":"","trans_title_bottom":"","btn_txt":"En savoir plus","trans_btn_txt":"","banner_color_style":"banner-green","enabled_dark_btn":false,"text_style":"light-theme"}},"16191035634f7425c1-1":{"type":"Collection","settings":{"banner_image":"shopify:\/\/shop_images\/saisirlist.gif","collection":"","enabled_info":true,"title_top":"Saisir votre liste de course produits","trans_title_top":"","title":"","trans_title":"","title_bottom":"","trans_title_bottom":"","btn_txt":"En savoir plus","trans_btn_txt":"","banner_color_style":"banner-green","enabled_dark_btn":false,"text_style":"light-theme"}},"16191035634f7425c1-2":{"type":"Collection","settings":{"banner_image":"shopify:\/\/shop_images\/ezgif.com-gif-maker_4.gif","collection":"","enabled_info":true,"title_top":"Essayer de nouvelles recettes plus simples","trans_title_top":"","title":"","trans_title":"","title_bottom":"","trans_title_bottom":"","btn_txt":"En savoir plus","trans_btn_txt":"","banner_color_style":"banner-green","enabled_dark_btn":false,"text_style":"light-theme"}},"94fc4483-317b-4090-ae1e-9c68f9e964dd":{"type":"Collection","settings":{"banner_image":"shopify:\/\/shop_images\/ezgif.com-gif-maker_4.gif","collection":"","enabled_info":true,"title_top":"Retrouver votre produit par sa photo","trans_title_top":"","title":"","trans_title":"","title_bottom":"","trans_title_bottom":"","btn_txt":"En savoir plus","trans_btn_txt":"","banner_color_style":"banner-green","enabled_dark_btn":false,"text_style":"light-theme"}}},"block_order":["16191035634f7425c1-0","16191035634f7425c1-1","16191035634f7425c1-2","94fc4483-317b-4090-ae1e-9c68f9e964dd"],"settings":{"enabled":true,"enabled_layout_2":true,"tab_title":"avec epirapid Vous pouvez...","use_equal_height":false,"image_ratio":"ratio_landscape","image_size":"cover","image_position2":"8"}},"1619109288e81ab7f6":{"type":"services","blocks":{"1619109288e81ab7f6-0":{"type":"Service","settings":{"services_title":"Epiconome","trans_services_title":"","services_desc":"Plus d'achats et moins de dépenses","trans_services_desc":""}},"1619109288e81ab7f6-1":{"type":"Service","settings":{"services_title":"Epizen","trans_services_title":"","services_desc":"Détendez vous, c'est plus de course, plus de plats et recettes","trans_services_desc":""}},"1619109288e81ab7f6-2":{"type":"Service","settings":{"services_title":"epixpress","trans_services_title":"","services_desc":"Livraison en un temps record","trans_services_desc":""}}},"block_order":["1619109288e81ab7f6-0","1619109288e81ab7f6-1","1619109288e81ab7f6-2"],"settings":{"enabled":true,"tab_title":"epirapid c'est..."}},"1619432762e958cf84":{"type":"slideshow","blocks":{"1619432762e958cf84-0":{"type":"Image","settings":{"slider":"shopify:\/\/shop_images\/Banner_01-B.gif","show_info":true,"heading_color":"#ffffff","top_heading":"","trans_top_heading":"","main_heading_color":"#7bc002","title_html":"","offer_html":"","shop_button":"Faites vous plaisir","trans_shop_button":"","shop_btn_url":"shopify:\/\/collections\/all"}}},"block_order":["1619432762e958cf84-0"],"settings":{"enabled":true,"alignment":"text-center","position":"p-center","enabled_overlay":false,"overlay_opacity":4,"slider_speed":3,"use_autoplay":true,"use_arrows":true,"use_dots":false,"use_loop":false}}},"content_for_index":["1619432762e958cf84","16191035634f7425c1","1618996591630da601","16189964209f69adb2","1619099473c85bae64","1619109288e81ab7f6","1569495574717","16172760213470fe16","1618919299d327db3e","16172743112c17da1b","1569491996226","1571476783856","1617879703be2a5e7a","16172081738e1718fd","1568788951664","1568787966576","1569494046757","1569469321673","1538114027245","16189962437f7a452d"]}}